sumatra/__init__.py
sumatra/commands.py
sumatra/core.py
sumatra/decorators.py
sumatra/launch.py
sumatra/parameters.py
sumatra/pfi.py
sumatra/programs.py
sumatra/projects.py
sumatra/records.py
sumatra/tee.py
sumatra/users.py
sumatra/cli/__init__.py
sumatra/cli/smt.py
sumatra/cli/smtweb.py
sumatra/datastore/__init__.py
sumatra/datastore/archivingfs.py
sumatra/datastore/base.py
sumatra/datastore/davfs.py
sumatra/datastore/filesystem.py
sumatra/datastore/mirroredfs.py
sumatra/dependency_finder/__init__.py
sumatra/dependency_finder/core.py
sumatra/dependency_finder/genesis.py
sumatra/dependency_finder/matlab.py
sumatra/dependency_finder/neuron.py
sumatra/dependency_finder/python.py
sumatra/dependency_finder/r.py
sumatra/external_scripts/script_introspect.R
sumatra/formatting/__init__.py
sumatra/formatting/latex_template.tex
sumatra/publishing/__init__.py
sumatra/publishing/utils.py
sumatra/publishing/latex/__init__.py
sumatra/publishing/latex/includefigure.py
sumatra/publishing/latex/sumatra.sty
sumatra/publishing/sphinxext/__init__.py
sumatra/publishing/sphinxext/sumatra_rst.py
sumatra/recordstore/__init__.py
sumatra/recordstore/base.py
sumatra/recordstore/http_store.py
sumatra/recordstore/serialization.py
sumatra/recordstore/shelve_store.py
sumatra/recordstore/django_store/__init__.py
sumatra/recordstore/django_store/models.py
sumatra/recordstore/django_store/tagging.py
sumatra/recordstore/django_store/tagging_utils.py
sumatra/recordstore/django_store/migrations/0001_initial.py
sumatra/recordstore/django_store/migrations/0002_tag_taggeditem.py
sumatra/recordstore/django_store/migrations/__init__.py
sumatra/versioncontrol/__init__.py
sumatra/versioncontrol/_bazaar.py
sumatra/versioncontrol/_git.py
sumatra/versioncontrol/_mercurial.py
sumatra/versioncontrol/_subversion.py
sumatra/versioncontrol/base.py
sumatra/web/__init__.py
sumatra/web/urls.py
sumatra/web/views.py
sumatra/web/static/css/animate.min.css
sumatra/web/static/css/bootstrap.min.css
sumatra-0.8.1.dist-info/licenses/LICENSE
sumatra-0.8.1.dist-info/METADATA
sumatra-0.8.1.dist-info/WHEEL
sumatra-0.8.1.dist-info/entry_points.txt
sumatra-0.8.1.dist-info/top_level.txt
sumatra-0.8.1.dist-info/RECORD
