Metadata-Version: 2.4
Name: Sumatra
Version: 0.8.1
Summary: A tool for automated tracking of computation-based scientific projects
Author-email: Sumatra authors and contributors <andrew.davison@cnrs.fr>
License-Expression: BSD-2-Clause
Project-URL: homepage, https://neuralensemble.org/sumatra
Project-URL: documentation, https://sumatra.readthedocs.io
Project-URL: repository, https://github.com/open-research/sumatra
Project-URL: download, http://pypi.python.org/pypi/sumatra
Keywords: computational science,simulation,analysis,project management
Classifier: Development Status :: 4 - Beta
Classifier: Environment :: Console
Classifier: Environment :: Web Environment
Classifier: Intended Audience :: Science/Research
Classifier: Natural Language :: English
Classifier: Operating System :: OS Independent
Classifier: Programming Language :: Python
Classifier: Programming Language :: Python :: 3
Classifier: Programming Language :: Python :: 3.9
Classifier: Programming Language :: Python :: 3.10
Classifier: Programming Language :: Python :: 3.11
Classifier: Programming Language :: Python :: 3.12
Classifier: Programming Language :: Python :: 3.13
Classifier: Topic :: Scientific/Engineering
Requires-Python: >=3.9
License-File: LICENSE
Requires-Dist: setuptools
Requires-Dist: packaging
Requires-Dist: parameters
Requires-Dist: pyyaml
Provides-Extra: git
Requires-Dist: GitPython; extra == "git"
Provides-Extra: hg
Requires-Dist: mercurial; extra == "hg"
Requires-Dist: hgapi; extra == "hg"
Provides-Extra: web
Requires-Dist: docutils; extra == "web"
Requires-Dist: Django<6; extra == "web"
Provides-Extra: remote
Requires-Dist: httplib2; extra == "remote"
Provides-Extra: postgres
Requires-Dist: psycopg2-binary; extra == "postgres"
Provides-Extra: mysql
Requires-Dist: mysqlclient; extra == "mysql"
Provides-Extra: latex
Requires-Dist: jinja2; extra == "latex"
Provides-Extra: sphinx
Requires-Dist: docutils; extra == "sphinx"
Provides-Extra: mpi
Requires-Dist: mpi4py; extra == "mpi"
Provides-Extra: docs
Requires-Dist: docutils; extra == "docs"
Requires-Dist: sphinx; extra == "docs"
Requires-Dist: sphinxawesome-theme; extra == "docs"
Provides-Extra: default
Requires-Dist: sumatra[git,remote,web]; extra == "default"
Provides-Extra: test
Requires-Dist: sarge; extra == "test"
Requires-Dist: numpy; extra == "test"
Requires-Dist: scipy; extra == "test"
Requires-Dist: matplotlib; extra == "test"
Requires-Dist: pillow; extra == "test"
Requires-Dist: pytest; extra == "test"
Requires-Dist: pytest-cov; extra == "test"
Requires-Dist: flake8; extra == "test"
Requires-Dist: selenium; extra == "test"
Requires-Dist: coveralls; extra == "test"
Provides-Extra: dev
Requires-Dist: sumatra[docs,git,hg,latex,mpi,mysql,postgres,remote,test,web]; extra == "dev"
Requires-Dist: build; extra == "dev"
Requires-Dist: twine; extra == "dev"
Requires-Dist: docker; extra == "dev"
Dynamic: license-file
